djsm/__init__.py
djsm/apps.py
djsm/exceptions.py
djsm/manager.py
djsm/misc.py
djsm/management/commands/change_cryptkeys.py
djsm/management/commands/djsm_cleanup.py
djsm/management/commands/djsm_reload_env.py
djsm/management/commands/update_secrets.py
djsm/management/commands/use_djsm.py
djsm-0.1.51.dist-info/LICENSE
djsm-0.1.51.dist-info/METADATA
djsm-0.1.51.dist-info/WHEEL
djsm-0.1.51.dist-info/top_level.txt
djsm-0.1.51.dist-info/RECORD
