Metadata-Version: 2.1
Name: djsm
Version: 0.1.51
Summary: Django package that allows you to store secrets encrypted in JSON and access them easily in your Django project.
Author-email: "Daniel T. Afolayan (ti-oluwa)" <tioluwa.dev@gmail.com>
Maintainer-email: "Daniel T. Afolayan (ti-oluwa)" <tioluwa.dev@gmail.com>
Project-URL: Homepage, https://github.com/ti-oluwa/djsm
Project-URL: Bug Tracker, https://github.com/ti-oluwa/djsm/issues
Project-URL: Repository, https://github.com/ti-oluwa/djsm
Keywords: Django,Django Secrets Encryption
Classifier: Programming Language :: Python :: 3
Classifier: License :: OSI Approved :: MIT License
Classifier: Operating System :: OS Independent
Classifier: Development Status :: 5 - Production/Stable
Classifier: Topic :: Security
Classifier: Intended Audience :: Developers
Classifier: Framework :: Django
Classifier: Environment :: Web Environment
Classifier: Natural Language :: English
Classifier: Typing :: Typed
Requires-Python: >=3.7
License-File: LICENSE
Requires-Dist: python-dotenv >=0.19.2
Requires-Dist: simple-file-handler >=0.0.1
Requires-Dist: dcrypt >=0.0.1
